{
	"info": {
		"_postman_id": "8af325ee-67c9-4537-89fa-a3cd0826505c",
		"name": "API Operadoras ANS",
		"schema": "https://schema.getpostman.com/json/collection/v2.1.0/collection.json",
		"_exporter_id": "43510648"
	},
	"item": [
		{
			"name": "Listar todas as operadoras",
			"request": {
				"method": "GET",
				"header": [],
				"url": {
					"raw": "http://localhost:5000/api/operadoras?limite=10",
					"protocol": "http",
					"host": [
						"localhost"
					],
					"port": "5000",
					"path": [
						"api",
						"operadoras"
					],
					"query": [
						{
							"key": "limite",
							"value": "10"
						}
					]
				}
			},
			"response": []
		},
		{
			"name": "Buscar por termo",
			"request": {
				"method": "GET",
				"header": [],
				"url": {
					"raw": "http://localhost:5000/api/operadoras?q=unimed&limite=10",
					"protocol": "http",
					"host": [
						"localhost"
					],
					"port": "5000",
					"path": [
						"api",
						"operadoras"
					],
					"query": [
						{
							"key": "q",
							"value": "unimed"
						},
						{
							"key": "limite",
							"value": "10"
						}
					]
				}
			},
			"response": []
		},
		{
			"name": "Status API",
			"request": {
				"method": "GET",
				"header": [],
				"url": {
					"raw": "http://localhost:5000/api",
					"protocol": "http",
					"host": [
						"localhost"
					],
					"port": "5000",
					"path": [
						"api"
					]
				}
			},
			"response": []
		},
		{
			"name": "Filtrar pot UF",
			"request": {
				"method": "GET",
				"header": [],
				"url": {
					"raw": "http://localhost:5000/api/operadoras?uf=SP&limite=10",
					"protocol": "http",
					"host": [
						"localhost"
					],
					"port": "5000",
					"path": [
						"api",
						"operadoras"
					],
					"query": [
						{
							"key": "uf",
							"value": "SP"
						},
						{
							"key": "limite",
							"value": "10"
						}
					]
				}
			},
			"response": []
		}
	]
}